robocorp_action_server-0.4.2.dist-info/RECORD
robocorp_action_server-0.4.2.dist-info/entry_points.txt
robocorp_action_server-0.4.2.dist-info/METADATA
robocorp_action_server-0.4.2.dist-info/WHEEL
robocorp/action_server/_whitelist.py
robocorp/action_server/__main__.py
robocorp/action_server/_protocols.py
robocorp/action_server/_static_contents.py
robocorp/action_server/_server_expose.py
robocorp/action_server/_models.py
robocorp/action_server/_slugify.py
robocorp/action_server/_gen_ids.py
robocorp/action_server/_actions_run_helpers.py
robocorp/action_server/_cli_helpers.py
robocorp/action_server/_download_rcc.py
robocorp/action_server/_actions_run.py
robocorp/action_server/__init__.py
robocorp/action_server/_settings.py
robocorp/action_server/_errors_action_server.py
robocorp/action_server/_api_action_package.py
robocorp/action_server/py.typed
robocorp/action_server/_new_project.py
robocorp/action_server/_api_run.py
robocorp/action_server/_server.py
robocorp/action_server/cli.py
robocorp/action_server/_actions_process_pool.py
robocorp/action_server/_runs_state_cache.py
robocorp/action_server/_server_websockets.py
robocorp/action_server/_selftest.py
robocorp/action_server/_database.py
robocorp/action_server/_rcc.py
robocorp/action_server/_actions_import.py
robocorp/action_server/_app.py
robocorp/action_server/README.md
robocorp/action_server/_errors.py
robocorp/action_server/vendored_deps/__init__.py
robocorp/action_server/vendored_deps/README.md
robocorp/action_server/vendored_deps/action_package_handling/__init__.py
robocorp/action_server/vendored_deps/action_package_handling/cli_errors.py
robocorp/action_server/vendored_deps/package_deps/_package_deps.py
robocorp/action_server/vendored_deps/package_deps/pypi_cloud.py
robocorp/action_server/vendored_deps/package_deps/_pip_deps.py
robocorp/action_server/vendored_deps/package_deps/_deps_protocols.py
robocorp/action_server/vendored_deps/package_deps/_conda_deps.py
robocorp/action_server/vendored_deps/package_deps/analyzer.py
robocorp/action_server/vendored_deps/package_deps/__init__.py
robocorp/action_server/vendored_deps/package_deps/conda_cloud.py
