Metadata-Version: 2.3
Name: robocorp-action-server
Version: 0.4.2
Summary: Robocorp local task server
License: Apache-2.0
Author: Fabio Z.
Author-email: fabio@robocorp.com
Requires-Python: >=3.10,<4.0
Classifier: License :: OSI Approved :: Apache Software License
Classifier: Programming Language :: Python :: 3
Classifier: Programming Language :: Python :: 3.10
Classifier: Programming Language :: Python :: 3.11
Classifier: Programming Language :: Python :: 3.12
Classifier: Programming Language :: Python :: 3.13
Requires-Dist: aiohttp (>=3.9.3,<4.0.0)
Requires-Dist: cryptography (>=42.0.5,<43.0.0)
Requires-Dist: fastapi (>=0.110.0,<0.111.0)
Requires-Dist: fastjsonschema (>=2.19.1,<3.0.0)
Requires-Dist: jsonschema (>=4.19.2,<5.0.0)
Requires-Dist: msgspec (>=0.18,<0.19)
Requires-Dist: psutil (>=5,<6)
Requires-Dist: pydantic (>=2.4.2,<3.0.0)
Requires-Dist: pyyaml (>=6,<7)
Requires-Dist: requests (>=2,<3)
Requires-Dist: robocorp-actions (>=0.2.0,<0.3.0)
Requires-Dist: termcolor (>=2.4.0,<3.0.0)
Requires-Dist: uvicorn (>=0.23.2,<0.24.0)
Requires-Dist: websockets (>=12.0,<13.0)
Project-URL: Repository, https://github.com/robocorp/robocorp/
